pyCommonClasses/Version.py
pyCommonClasses/__init__.py
pyCommonClasses-0.2.3.dist-info/LICENSE.md
pyCommonClasses-0.2.3.dist-info/METADATA
pyCommonClasses-0.2.3.dist-info/WHEEL
pyCommonClasses-0.2.3.dist-info/top_level.txt
pyCommonClasses-0.2.3.dist-info/RECORD
